dragulacontainer/Dragulacontainer.py
dragulacontainer/__init__.py
dragulacontainer/_imports_.py
dragulacontainer/dragulacontainer.min.js
dragulacontainer/dragulacontainer.min.js.map
dragulacontainer/metadata.json
dragulacontainer/package-info.json
dragulacontainer-0.0.4.dist-info/LICENSE
dragulacontainer-0.0.4.dist-info/METADATA
dragulacontainer-0.0.4.dist-info/WHEEL
dragulacontainer-0.0.4.dist-info/top_level.txt
dragulacontainer-0.0.4.dist-info/RECORD
